src/reaction_timer.v
`default_nettype none
`timescale 1ns / 1ps

module reaction_timer (
    input wire clk,
    input wire rst_n,
    input wire start_stop,
    output reg [15:0] reaction_time,
    output reg [6:0] seg0, seg1, seg2, seg3,
    output reg led
);

  reg [31:0] counter;
  reg running;

  always @(posedge clk or negedge rst_n) begin
    if (!rst_n) begin
      counter <= 0;
      reaction_time <= 0;
      running <= 0;
      led <= 0;
      seg0 <= 7'b1111111;
      seg1 <= 7'b1111111;
      seg2 <= 7'b1111111;
      seg3 <= 7'b1111111;
    end else begin
      if (start_stop) begin
        if (running) begin
          reaction_time <= counter[15:0];
          running <= 0;
          led <= 0;
          counter <= 0;
        end else begin
          running <= 1;
          led <= 1;
        end
      end

      if (running) begin
        counter <= counter + 1;
      end

      // Update 7-segment displays
      seg0 <= decode_7segment(reaction_time[3:0]);
      seg1 <= decode_7segment(reaction_time[7:4]);
      seg2 <= decode_7segment(reaction_time[11:8]);
      seg3 <= decode_7segment(reaction_time[15:12]);
    end
  end

  function [6:0] decode_7segment;
    input [3:0] digit;
    begin
      case (digit)
        4'd0: decode_7segment = 7'b1000000;
        4'd1: decode_7segment = 7'b1111001;
        4'd2: decode_7segment = 7'b0100100;
        4'd3: decode_7segment = 7'b0110000;
        4'd4: decode_7segment = 7'b0011001;
        4'd5: decode_7segment = 7'b0010010;
        4'd6: decode_7segment = 7'b0000010;
        4'd7: decode_7segment = 7'b1111000;
        4'd8: decode_7segment = 7'b0000000;
        4'd9: decode_7segment = 7'b0010000;
        default: decode_7segment = 7'b1111111;
      endcase
    end
  endfunction

endmodule

src/tt_um_reaction_timer.v
`default_nettype none
`timescale 1ns / 1ps

module tt_um_reaction_timer (
    input wire [7:0] ui_in,
    output wire [7:0] uo_out,
    input wire [7:0] uio_in,
    output wire [7:0] uio_out,
    output wire [7:0] uio_oe,
    input wire ena,
    input wire clk,
    input wire rst_n
);

  wire [15:0] reaction_time;
  wire [6:0] seg0, seg1, seg2, seg3;
  wire led;

  reaction_timer rt (
    .clk(clk),
    .rst_n(rst_n),
    .start_stop(ui_in[0]),
    .reaction_time(reaction_time),
    .seg0(seg0),
    .seg1(seg1),
    .seg2(seg2),
    .seg3(seg3),
    .led(led)
  );

  assign uo_out[0] = led;

  // Map 7-segment displays to uio_out
  assign uio_out[7:0] = seg0;
  assign uio_out[15:8] = seg1;
  assign uio_out[23:16] = seg2;
  assign uio_out[31:24] = seg3;

  // Output enable for uio_out
  assign uio_oe = 8'hFF;

endmodule

test/tb.v
`default_nettype none
`timescale 1ns / 1ps

module tb ();

  // Dump the signals to a VCD file. You can view it with gtkwave.
  initial begin
    $dumpfile("tb.vcd");
    $dumpvars(0, tb);
    #1;
  end

  // Wire up the inputs and outputs
  reg clk;
  reg rst_n;
  reg [7:0] ui_in;
  wire [7:0] uo_out;
  wire [31:0] uio_out; // Updated width to 7
  wire [7:0] uio_oe;
  reg ena;

  // Instantiate the DUT (Device Under Test)
  tt_um_reaction_timer uut (
      .clk     (clk),
      .rst_n   (rst_n),
      .ui_in   (ui_in),
      .uo_out  (uo_out),
      .uio_in  (8'b0),   // Not used in this testbench
      .uio_out (uio_out),
      .uio_oe  (uio_oe),
      .ena     (ena)
  );

  // Generate clock
  initial begin
    clk = 0;
    forever #10 clk = ~clk; // 50 MHz clock
  end

  // Initial conditions
  initial begin
    rst_n = 0;
    ui_in = 8'b0;
    ena = 1'b0;
    #100 rst_n = 1;
    ena = 1'b1;
    #300 ui_in[0] = 1;  // Press button
    #20 ui_in[0] = 0;   // Release button
    #30 rst_n = 0;      // Reset
    #30 rst_n = 1;      // Release reset
    #300 ui_in[0] = 1;  // Press button again
    #20 ui_in[0] = 0;   // Release button again
  end

  // Stop simulation after 10 seconds
  initial begin
    #100000000; // 10 seconds in nanoseconds (10 * 10^9 ns)
    $finish;
  end

endmodule

test/tb.vcd
$date
	Fri Jul 26 13:32:27 2024
$end
$version
	Icarus Verilog
$end
$timescale
	1ps
$end
$scope module tb $end
$var wire 8 ! uio_oe [7:0] $end
$var wire 8 " uo_out [7:0] $end
$var wire 32 # uio_out [31:0] $end
$var reg 1 $ clk $end
$var reg 1 % ena $end
$var reg 1 & rst_n $end
$var reg 8 ' ui_in [7:0] $end
$scope module uut $end
$var wire 1 $ clk $end
$var wire 1 % ena $end
$var wire 1 & rst_n $end
$var wire 8 ( ui_in [7:0] $end
$var wire 8 ) uio_in [7:0] $end
$var wire 8 * uio_oe [7:0] $end
$var wire 8 + uo_out [7:0] $end
$var wire 8 , uio_out [7:0] $end
$var wire 7 - seg3 [6:0] $end
$var wire 7 . seg2 [6:0] $end
$var wire 7 / seg1 [6:0] $end
$var wire 7 0 seg0 [6:0] $end
$var wire 16 1 reaction_time [15:0] $end
$var wire 1 2 led $end
$scope module rt $end
$var wire 1 $ clk $end
$var wire 1 & rst_n $end
$var wire 1 3 start_stop $end
$var reg 32 4 counter [31:0] $end
$var reg 1 2 led $end
$var reg 16 5 reaction_time [15:0] $end
$var reg 1 6 running $end
$var reg 7 7 seg0 [6:0] $end
$var reg 7 8 seg1 [6:0] $end
$var reg 7 9 seg2 [6:0] $end
$var reg 7 : seg3 [6:0] $end
$scope function decode_7segment $end
$var reg 4 ; digit [3:0] $end
$upscope $end
$upscope $end
$upscope $end
$upscope $end
$enddefinitions $end
#0
$dumpvars
bx ;
b1111111 :
b1111111 9
b1111111 8
b1111111 7
06
b0 5
b0 4
03
02
b0 1
b1111111 0
b1111111 /
b1111111 .
b1111111 -
b1111111 ,
bz0 +
b11111111 *
b0 )
b0 (
b0 '
0&
0%
0$
b1111111 #
bz0 "
b11111111 !
$end
#10000
1%
1&
1$
#20000
0$
#30000
13
b1 '
b1 (
b1000000 -
b1000000 :
b1000000 .
b1000000 9
b1000000 /
b1000000 8
b1000000 #
b1000000 ,
b1000000 0
b1000000 7
b0 ;
1$
#40000
0$
#50000
bz1 "
bz1 +
12
16
1$
#60000
0$
#70000
b1 4
bz0 "
bz0 +
02
06
1$
#80000
0$
#90000
bz1 "
bz1 +
12
16
1$
#100000
0$
#110000
b10 4
bz0 "
bz0 +
02
06
b1 1
b1 5
1$
#120000
0$
#130000
b1111001 #
b1111001 ,
b1111001 0
b1111001 7
bz1 "
bz1 +
12
16
b0 ;
1$
#140000
0$
#150000
b11 4
bz0 "
bz0 +
02
06
b10 1
b10 5
b0 ;
1$
#160000
0$
#170000
b100100 #
b100100 ,
b100100 0
b100100 7
bz1 "
bz1 +
12
16
b0 ;
1$
#180000
0$
#190000
b100 4
bz0 "
bz0 +
02
06
b11 1
b11 5
b0 ;
1$
#200000
0$
#210000
b110000 #
b110000 ,
b110000 0
b110000 7
bz1 "
bz1 +
12
16
b0 ;
1$
#220000
0$
#230000
03
b0 '
b0 (
b101 4
bz0 "
bz0 +
02
06
b100 1
b100 5
b0 ;
1$
#240000
0$
#250000
b11001 #
b11001 ,
b11001 0
b11001 7
b0 ;
1$
#260000
0$
#270000
b0 ;
1$
#280000
0$
#290000
b0 ;
1$
#300000
0$
#310000
b0 ;
1$
#320000
0$
#330000
b0 ;
1$
#340000
0$
#350000
b0 ;
1$
#360000
0$
#370000
b0 ;
1$
#380000
0$
#390000
b0 ;
1$
#400000
13
0$
b1 '
b1 (
#410000
bz1 "
bz1 +
12
16
b0 ;
1$
#420000
03
0$
b0 '
b0 (
#430000
b110 4
b0 ;
1$
#440000
0$
#450000
b1111111 -
b1111111 :
b1111111 .
b1111111 9
b1111111 /
b1111111 8
b1111111 #
b1111111 ,
b1111111 0
b1111111 7
bz0 "
bz0 +
02
06
b0 1
b0 5
b0 4
1$
0&
